toohardman_pkg/__init__.py
toohardman_pkg_dosoos-0.0.1.dist-info/LICENSE
toohardman_pkg_dosoos-0.0.1.dist-info/METADATA
toohardman_pkg_dosoos-0.0.1.dist-info/WHEEL
toohardman_pkg_dosoos-0.0.1.dist-info/top_level.txt
toohardman_pkg_dosoos-0.0.1.dist-info/RECORD
