Metadata-Version: 2.1
Name: toohardman-pkg-dosoos
Version: 0.0.1
Summary: A man introduce package
Home-page: UNKNOWN
Author: dosoos
Author-email: dosoos94@gmail.com
License: UNKNOWN
Platform: UNKNOWN
Classifier: Programming Language :: Python :: 3
Classifier: License :: OSI Approved :: MIT License
Classifier: Operating System :: OS Independent
License-File: LICENSE
